gravity_core_api/__init__.py
gravity_core_api/functions.py
gravity_core_api/general_methods.py
gravity_core_api/main.py
gravity_core_api/settings.py
gravity_core_api/operate_user_commands/__init__.py
gravity_core_api/operate_user_commands/functions.py
gravity_core_api/operate_user_commands/main.py
gravity_core_api/operate_user_commands/service_functions.py
gravity_core_api/operate_user_commands/settings.py
gravity_core_api/operate_user_commands/tests/__init__.py
gravity_core_api/operate_user_commands/tests/client_test.py
gravity_core_api/operate_user_commands/tests/test_commands.py
gravity_core_api/tests/__init__.py
gravity_core_api/tests/ar_support_commands_test.py
gravity_core_api/tests/client_test.py
gravity_core_api/tests/command_execution_test.py
gravity_core_api/tests/general_function_test.py
gravity_core_api/tests/test_ar.py
gravity_core_api/tests/test_settings.py
gravity_core_api/tests/wserver_upd_test.py
gravity_core_api/wserver_update_commands/__init__.py
gravity_core_api/wserver_update_commands/functions.py
gravity_core_api/wserver_update_commands/main.py
gravity_core_api/wserver_update_commands/service_functions.py
gravity_core_api/wserver_update_commands/settings.py
gravity_core_api/wserver_update_commands/tests/__init__.py
gravity_core_api/wserver_update_commands/tests/client_test.py
gravity_core_api/wserver_update_commands/tests/test_commands.py
gravity_core_api_cm_beta-0.164.dist-info/LICENSE
gravity_core_api_cm_beta-0.164.dist-info/METADATA
gravity_core_api_cm_beta-0.164.dist-info/WHEEL
gravity_core_api_cm_beta-0.164.dist-info/top_level.txt
gravity_core_api_cm_beta-0.164.dist-info/RECORD
