Metadata-Version: 2.1
Name: gravity-core-api-cm-beta
Version: 0.164
Summary: UNKNOWN
Home-page: UNKNOWN
Author: PunchyArchy
Author-email: ksmdrmvscthny@gmail.com
License: UNKNOWN
Platform: UNKNOWN
License-File: LICENSE
Requires-Dist: witapi
